xflow/__init__.py
xflow/_api_registry.py
xflow/_version.py
xflow/data/__init__.py
xflow/data/pipeline.py
xflow/data/provider.py
xflow/data/transform.py
xflow/evaluation/__init__.py
xflow/evaluation/metrics.py
xflow/extensions/__init__.py
xflow/extensions/eda/__init__.py
xflow/extensions/eda/plot.py
xflow/extensions/physics/__init__.py
xflow/extensions/physics/beam.py
xflow/extensions/physics/callback.py
xflow/extensions/physics/loss.py
xflow/extensions/physics/transform.py
xflow/extensions/style/__init__.py
xflow/extensions/style/aps.py
xflow/models/__init__.py
xflow/models/base.py
xflow/models/utils.py
xflow/trainers/__init__.py
xflow/trainers/callback.py
xflow/trainers/trainer.py
xflow/utils/__init__.py
xflow/utils/config.py
xflow/utils/dataframe.py
xflow/utils/decorator.py
xflow/utils/helper.py
xflow/utils/io.py
xflow/utils/metadata.py
xflow/utils/parser.py
xflow/utils/sql.py
xflow/utils/typing.py
xflow/utils/visualization.py
xflow/validation/schemas.py
xflow/validation/validator.py
xflow_py-0.1.26.dist-info/licenses/LICENSE
xflow_py-0.1.26.dist-info/METADATA
xflow_py-0.1.26.dist-info/WHEEL
xflow_py-0.1.26.dist-info/top_level.txt
xflow_py-0.1.26.dist-info/RECORD
