Metadata-Version: 2.4
Name: xflow-py
Version: 0.1.26
Summary: A modular ML framework for training and evaluation tasks
Author: Qiyuan Xu
License: MIT License
Project-URL: Homepage, https://github.com/Andrew-XQY/XFlow
Keywords: machine-learning,tensorflow,data-pipeline
Classifier: License :: OSI Approved :: MIT License
Classifier: Programming Language :: Python :: 3
Classifier: Programming Language :: Python :: 3.12
Classifier: Topic :: Scientific/Engineering :: Artificial Intelligence
Requires-Python: >=3.8
License-File: LICENSE
Requires-Dist: numpy
Requires-Dist: pandas
Requires-Dist: tqdm
Requires-Dist: matplotlib
Requires-Dist: pyyaml>=6.0
Requires-Dist: typing-extensions>=4.0.0
Provides-Extra: validation
Requires-Dist: pydantic>=2.0.0; extra == "validation"
Provides-Extra: ml
Requires-Dist: tensorflow==2.16.2; extra == "ml"
Requires-Dist: keras==3.4.1; extra == "ml"
Provides-Extra: viz
Requires-Dist: matplotlib; extra == "viz"
Requires-Dist: opencv-python; extra == "viz"
Provides-Extra: dev
Requires-Dist: mypy; extra == "dev"
Requires-Dist: pre-commit; extra == "dev"
Requires-Dist: black; extra == "dev"
Requires-Dist: isort; extra == "dev"
Provides-Extra: docs
Requires-Dist: sphinx>=7.0.0; extra == "docs"
Requires-Dist: furo>=2024.1.29; extra == "docs"
Requires-Dist: setuptools_scm; extra == "docs"
Requires-Dist: pyyaml>=6.0; extra == "docs"
Provides-Extra: all
Requires-Dist: xflow-py[ml,validation,viz]; extra == "all"
Dynamic: license-file
